Stefan_T_project/Stefan.py
Stefan_T_project/__init__.py
Stefan_T_project-0.1.2.dist-info/METADATA
Stefan_T_project-0.1.2.dist-info/WHEEL
Stefan_T_project-0.1.2.dist-info/top_level.txt
Stefan_T_project-0.1.2.dist-info/RECORD
