Metadata-Version: 2.1
Name: Stefan-T-project
Version: 0.1.2
Summary: First T
Home-page: UNKNOWN
Author: Stefan-Tohati
Author-email: stef20_2007@yahoo.com
License: UNKNOWN
Platform: UNKNOWN
